pybox/__about__.py
pybox/__init__.py
pybox/base.py
pybox/local.py
pybox/remote.py
pybox/schema.py
pybox/utils.py
pppybox-0.0.18.dist-info/METADATA
pppybox-0.0.18.dist-info/WHEEL
pppybox-0.0.18.dist-info/licenses/LICENSE
pppybox-0.0.18.dist-info/RECORD
