Metadata-Version: 2.4
Name: pppybox
Version: 0.0.18
Project-URL: Documentation, https://github.com/edwardzjl/pybox#readme
Project-URL: Issues, https://github.com/edwardzjl/pybox/issues
Project-URL: Source, https://github.com/edwardzjl/pybox
Author-email: Junlin Zhou <jameszhou2108@hotmail.com>
License:                                  Apache License
License-File: LICENSE
Classifier: Development Status :: 4 - Beta
Classifier: Programming Language :: Python
Classifier: Programming Language :: Python :: 3.8
Classifier: Programming Language :: Python :: 3.9
Classifier: Programming Language :: Python :: 3.10
Classifier: Programming Language :: Python :: 3.11
Classifier: Programming Language :: Python :: 3.12
Classifier: Programming Language :: Python :: Implementation :: CPython
Classifier: Programming Language :: Python :: Implementation :: PyPy
Requires-Python: >=3.8
Requires-Dist: aiohttp[speedups]>=3.9.3
Requires-Dist: pydantic>=2
Requires-Dist: python-dotenv>=1
Requires-Dist: requests>=2
Requires-Dist: websockets>=12
Provides-Extra: local
Requires-Dist: ipykernel>=6.26.0; extra == 'local'
Requires-Dist: ipython>=8.18.1; extra == 'local'
Requires-Dist: jupyter-client>=8.6.0; extra == 'local'
